custom_grid_plot/__init__.py
custom_grid_plot/example.py
custom_grid_plot/frontend/build/asset-manifest.json
custom_grid_plot/frontend/build/bootstrap.min.css
custom_grid_plot/frontend/build/index.html
custom_grid_plot/frontend/build/static/css/main.ee667e9b.css
custom_grid_plot/frontend/build/static/css/main.ee667e9b.css.map
custom_grid_plot/frontend/build/static/js/main.85cfca62.js
custom_grid_plot/frontend/build/static/js/main.85cfca62.js.LICENSE.txt
custom_grid_plot/frontend/build/static/js/main.85cfca62.js.map
custom_grid_chart-0.0.1.dist-info/LICENSE
custom_grid_chart-0.0.1.dist-info/METADATA
custom_grid_chart-0.0.1.dist-info/WHEEL
custom_grid_chart-0.0.1.dist-info/top_level.txt
custom_grid_chart-0.0.1.dist-info/RECORD
